flexrpc/__init__.py
flexrpc-0.0.dist-info/LICENSE.txt
flexrpc-0.0.dist-info/METADATA
flexrpc-0.0.dist-info/WHEEL
flexrpc-0.0.dist-info/top_level.txt
flexrpc-0.0.dist-info/RECORD
