Metadata-Version: 2.1
Name: flexrpc
Version: 0.0
Author-email: Florian Scherf <mail@florianscherf.de>
License: MIT License
Requires-Python: >=3.8
License-File: LICENSE.txt
Provides-Extra: dev
Requires-Dist: build ; extra == 'dev'
Requires-Dist: twine ; extra == 'dev'
Requires-Dist: tox ==4.23.2 ; extra == 'dev'
Requires-Dist: pytest ==8.3.3 ; extra == 'dev'
Requires-Dist: coverage ==7.6.1 ; extra == 'dev'
